{"name":"Video Tutorials for classes taken at FIU","tagline":"Video Tutorials for classes taken at FIU ","body":"Video Tutorials for classes taken at FIU.\r\n\r\nThis video project was made for CEN 5011 - Advanced Software Engineering - Fall 2014\r\n[https://github.com/cguid001/VideoTutorials/blob/master/CEN5011_VideoProject_720.mp4](https://github.com/cguid001/VideoTutorials/blob/master/CEN5011_VideoProject_720.mp4)\r\n\r\n` <!-- MAIN CONTENT -->\r\n    <div id=\"main_content_wrap\" class=\"outer\">\r\n      <section id=\"main_content\" class=\"inner\">\r\n        <video width=\"800\" controls preload>\r\n\t\t\t<source src=\"https://github.com/cguid001/VideoTutorials/blob/master/CEN5011_VideoProject_720.mp4\">  \r\n\t\t\tYour browser does not support the video tag.\r\n\t\t</video>\r\n      </section>\r\n    </div>`\r\n","google":"","note":"Don't delete this file! It's used internally to help with page regeneration."}